{"type": "FeatureCollection", "id": "https://research-squirrel-engineers.github.io/osm2lod/1622870447_geom", "name": "1622870447_geom", "features": [{"type": "Feature", "id": "http://openstreetmap.org/node/1622870447", "name": "", "dateprops": [], "properties": {"http://purl.org/dc/terms/created": ["2025-12-19T10:32:09.810385+00:00"], "http://purl.org/dc/terms/identifier": ["osm:node/1622870447"], "http://purl.org/dc/terms/isPartOf": ["https://research-squirrel-engineers.github.io/osm2lod/holywells__2025-12-19_103209Z"], "http://rdfs.org/ns/void#inDataset": ["http://openstreetmap.org/osm2rdf"], "http://www.opengis.net/ont/geosparql#hasGeometry": ["https://research-squirrel-engineers.github.io/osm2lod/1622870447_geom"], "http://www.w3.org/1999/02/22-rdf-syntax-ns#type": ["http://www.cidoc-crm.org/cidoc-crm/E26_Physical_Feature", "http://www.w3.org/ns/dcat#Dataset", "https://research-squirrel-engineers.github.io/osm2lod/OSMEntity"], "http://www.w3.org/2000/01/rdf-schema#label": ["Saint Colmcille's Well"], "http://xmlns.com/foaf/0.1/primaryTopic": ["http://openstreetmap.org/node/1622870447"], "https://research-squirrel-engineers.github.io/osm2lod/exportType": ["holywells"], "https://research-squirrel-engineers.github.io/osm2lod/osmtag__alt_name": ["Saint Columbkille's Well"], "https://research-squirrel-engineers.github.io/osm2lod/osmtag__description": ["Stone-lined water well. A stream of water flows out of it, down the embankment then along and over the road a little further to the south."], "https://research-squirrel-engineers.github.io/osm2lod/osmtag__historic": ["ruins"], "https://research-squirrel-engineers.github.io/osm2lod/osmtag__name": ["Saint Colmcille's Well"], "https://research-squirrel-engineers.github.io/osm2lod/osmtag__natural": ["spring"], "https://research-squirrel-engineers.github.io/osm2lod/osmtag__place_of_worship": ["holy_well"], "https://research-squirrel-engineers.github.io/osm2lod/osmtag__religion": ["christian"], "https://research-squirrel-engineers.github.io/osm2lod/osmtag__source": ["Bing Streetside 2018-07-11"]}, "geometry": {"type": "Point", "coordinates": [-6.461453, 52.8562566], "crs": "4326"}, "crs": "EPSG:4326"}], "numberMatched": 1, "numberReturned": 1, "bbox": [-6.461453, 52.8562566, -6.461453, 52.8562566], "crs": "http://www.opengis.net/def/crs/EPSG/0/EPSG:4326"}