{"type": "FeatureCollection", "id": "https://research-squirrel-engineers.github.io/osm2lod/11955670778_geom", "name": "11955670778_geom", "features": [{"type": "Feature", "id": "http://openstreetmap.org/node/11955670778", "name": "", "dateprops": [], "properties": {"http://purl.org/dc/terms/created": ["2025-12-19T10:32:05.532368+00:00"], "http://purl.org/dc/terms/identifier": ["osm:node/11955670778"], "http://purl.org/dc/terms/isPartOf": ["https://research-squirrel-engineers.github.io/osm2lod/ogham__2025-12-19_103205Z"], "http://rdfs.org/ns/void#inDataset": ["http://openstreetmap.org/osm2rdf"], "http://www.opengis.net/ont/geosparql#hasGeometry": ["https://research-squirrel-engineers.github.io/osm2lod/11955670778_geom"], "http://www.w3.org/1999/02/22-rdf-syntax-ns#type": ["http://www.cidoc-crm.org/cidoc-crm/E22_Human_Made_Object", "http://www.w3.org/ns/dcat#Dataset", "https://research-squirrel-engineers.github.io/osm2lod/OSMEntity"], "http://www.w3.org/2000/01/rdf-schema#label": ["UCC 23"], "http://xmlns.com/foaf/0.1/primaryTopic": ["http://openstreetmap.org/node/11955670778"], "https://research-squirrel-engineers.github.io/osm2lod/exportType": ["ogham"], "https://research-squirrel-engineers.github.io/osm2lod/osmtag__historic": ["ogham_stone"], "https://research-squirrel-engineers.github.io/osm2lod/osmtag__name": ["UCC 23"], "https://research-squirrel-engineers.github.io/osm2lod/osmtag__source": ["survey"]}, "geometry": {"type": "Point", "coordinates": [-8.4923901, 51.8936754], "crs": "4326"}, "crs": "EPSG:4326"}], "numberMatched": 1, "numberReturned": 1, "bbox": [-8.4923901, 51.8936754, -8.4923901, 51.8936754], "crs": "http://www.opengis.net/def/crs/EPSG/0/EPSG:4326"}