{"type": "FeatureCollection", "id": "https://research-squirrel-engineers.github.io/osm2lod/8278980324_geom", "name": "8278980324_geom", "features": [{"type": "Feature", "id": "http://openstreetmap.org/node/8278980324", "name": "", "dateprops": [], "properties": {"http://purl.org/dc/terms/created": ["2025-12-19T10:32:09.810385+00:00"], "http://purl.org/dc/terms/identifier": ["osm:node/8278980324"], "http://purl.org/dc/terms/isPartOf": ["https://research-squirrel-engineers.github.io/osm2lod/holywells__2025-12-19_103209Z"], "http://rdfs.org/ns/void#inDataset": ["http://openstreetmap.org/osm2rdf"], "http://www.opengis.net/ont/geosparql#hasGeometry": ["https://research-squirrel-engineers.github.io/osm2lod/8278980324_geom"], "http://www.w3.org/1999/02/22-rdf-syntax-ns#type": ["http://www.cidoc-crm.org/cidoc-crm/E26_Physical_Feature", "http://www.w3.org/ns/dcat#Dataset", "https://research-squirrel-engineers.github.io/osm2lod/OSMEntity"], "http://www.w3.org/2000/01/rdf-schema#label": ["Church Well", "Tobar an Teampaill"], "http://www.w3.org/2002/07/owl#sameAs": ["http://wikidata.org/entity/Q122303248"], "http://xmlns.com/foaf/0.1/primaryTopic": ["http://openstreetmap.org/node/8278980324"], "https://research-squirrel-engineers.github.io/osm2lod/exportType": ["holywells"], "https://research-squirrel-engineers.github.io/osm2lod/osmtag__alt_name": ["Kiltrassy Well"], "https://research-squirrel-engineers.github.io/osm2lod/osmtag__natural": ["spring"], "https://research-squirrel-engineers.github.io/osm2lod/osmtag__note": ["Alt name is Kiltrassy well, despite it being in Oldcastle."], "https://research-squirrel-engineers.github.io/osm2lod/osmtag__place_of_worship": ["holy_well"], "https://research-squirrel-engineers.github.io/osm2lod/osmtag__source": ["survey"], "https://research-squirrel-engineers.github.io/osm2lod/osmtag__wikidata": ["Q122303248"]}, "geometry": {"type": "Point", "coordinates": [-7.4021043, 52.4419089], "crs": "4326"}, "crs": "EPSG:4326"}], "numberMatched": 1, "numberReturned": 1, "bbox": [-7.4021043, 52.4419089, -7.4021043, 52.4419089], "crs": "http://www.opengis.net/def/crs/EPSG/0/EPSG:4326"}