{"type": "FeatureCollection", "id": "https://research-squirrel-engineers.github.io/osm2lod/916802123_geom", "name": "916802123_geom", "features": [{"type": "Feature", "id": "http://openstreetmap.org/node/916802123", "name": "", "dateprops": [], "properties": {"http://purl.org/dc/terms/created": ["2025-12-19T10:32:09.810385+00:00"], "http://purl.org/dc/terms/identifier": ["osm:node/916802123"], "http://purl.org/dc/terms/isPartOf": ["https://research-squirrel-engineers.github.io/osm2lod/holywells__2025-12-19_103209Z"], "http://rdfs.org/ns/void#inDataset": ["http://openstreetmap.org/osm2rdf"], "http://www.opengis.net/ont/geosparql#hasGeometry": ["https://research-squirrel-engineers.github.io/osm2lod/916802123_geom"], "http://www.w3.org/1999/02/22-rdf-syntax-ns#type": ["http://www.cidoc-crm.org/cidoc-crm/E26_Physical_Feature", "http://www.w3.org/ns/dcat#Dataset", "https://research-squirrel-engineers.github.io/osm2lod/OSMEntity"], "http://www.w3.org/2000/01/rdf-schema#label": ["Saint Colmcille's Well"], "http://xmlns.com/foaf/0.1/primaryTopic": ["http://openstreetmap.org/node/916802123"], "https://research-squirrel-engineers.github.io/osm2lod/exportType": ["holywells"], "https://research-squirrel-engineers.github.io/osm2lod/osmtag__name": ["Saint Colmcille's Well"], "https://research-squirrel-engineers.github.io/osm2lod/osmtag__place_of_worship": ["holy_well"], "https://research-squirrel-engineers.github.io/osm2lod/osmtag__religion": ["christian"]}, "geometry": {"type": "Point", "coordinates": [-6.2226739, 53.4559438], "crs": "4326"}, "crs": "EPSG:4326"}], "numberMatched": 1, "numberReturned": 1, "bbox": [-6.2226739, 53.4559438, -6.2226739, 53.4559438], "crs": "http://www.opengis.net/def/crs/EPSG/0/EPSG:4326"}