{"type": "FeatureCollection", "id": "https://research-squirrel-engineers.github.io/osm2lod/452289802_geom", "name": "452289802_geom", "features": [{"type": "Feature", "id": "http://openstreetmap.org/node/452289802", "name": "", "dateprops": [], "properties": {"http://purl.org/dc/terms/created": ["2025-12-19T10:32:05.532368+00:00"], "http://purl.org/dc/terms/identifier": ["osm:node/452289802"], "http://purl.org/dc/terms/isPartOf": ["https://research-squirrel-engineers.github.io/osm2lod/ogham__2025-12-19_103205Z"], "http://rdfs.org/ns/void#inDataset": ["http://openstreetmap.org/osm2rdf"], "http://www.opengis.net/ont/geosparql#hasGeometry": ["https://research-squirrel-engineers.github.io/osm2lod/452289802_geom"], "http://www.w3.org/1999/02/22-rdf-syntax-ns#type": ["http://www.cidoc-crm.org/cidoc-crm/E22_Human_Made_Object", "http://www.w3.org/ns/dcat#Dataset", "https://research-squirrel-engineers.github.io/osm2lod/OSMEntity"], "http://www.w3.org/2000/01/rdf-schema#label": ["Darrynane Beg Ogham Stone", "Cloch Oghaim Dhoire Fh\u00edon\u00e1in Beag"], "http://www.w3.org/2002/07/owl#sameAs": ["http://wikidata.org/entity/Q42377707"], "http://xmlns.com/foaf/0.1/primaryTopic": ["http://openstreetmap.org/node/452289802"], "https://research-squirrel-engineers.github.io/osm2lod/exportType": ["ogham"], "https://research-squirrel-engineers.github.io/osm2lod/osmtag__historic": ["ogham_stone"], "https://research-squirrel-engineers.github.io/osm2lod/osmtag__name": ["Darrynane Beg Ogham Stone"], "https://research-squirrel-engineers.github.io/osm2lod/osmtag__wikidata": ["Q42377707"], "https://research-squirrel-engineers.github.io/osm2lod/osmtag__wikipedia": ["Darrynane Beg Ogham Stone"]}, "geometry": {"type": "Point", "coordinates": [-10.1218702, 51.7640921], "crs": "4326"}, "crs": "EPSG:4326"}], "numberMatched": 1, "numberReturned": 1, "bbox": [-10.1218702, 51.7640921, -10.1218702, 51.7640921], "crs": "http://www.opengis.net/def/crs/EPSG/0/EPSG:4326"}