{"type": "FeatureCollection", "id": "https://research-squirrel-engineers.github.io/osm2lod/9020294868_geom", "name": "9020294868_geom", "features": [{"type": "Feature", "id": "http://openstreetmap.org/node/9020294868", "name": "", "dateprops": [], "properties": {"http://purl.org/dc/terms/created": ["2025-12-19T10:32:09.810385+00:00"], "http://purl.org/dc/terms/identifier": ["osm:node/9020294868"], "http://purl.org/dc/terms/isPartOf": ["https://research-squirrel-engineers.github.io/osm2lod/holywells__2025-12-19_103209Z"], "http://rdfs.org/ns/void#inDataset": ["http://openstreetmap.org/osm2rdf"], "http://www.opengis.net/ont/geosparql#hasGeometry": ["https://research-squirrel-engineers.github.io/osm2lod/9020294868_geom"], "http://www.w3.org/1999/02/22-rdf-syntax-ns#type": ["http://www.cidoc-crm.org/cidoc-crm/E26_Physical_Feature", "http://www.w3.org/ns/dcat#Dataset", "https://research-squirrel-engineers.github.io/osm2lod/OSMEntity"], "http://www.w3.org/2000/01/rdf-schema#label": ["Tobar P\u00e1rtal\u00e1in"], "http://xmlns.com/foaf/0.1/primaryTopic": ["http://openstreetmap.org/node/9020294868"], "https://research-squirrel-engineers.github.io/osm2lod/exportType": ["holywells"], "https://research-squirrel-engineers.github.io/osm2lod/osmtag__denomination": ["roman_catholic"], "https://research-squirrel-engineers.github.io/osm2lod/osmtag__description": ["Misinterpreted as St Bartholomew's well on old maps but it is unlikely this Partal\u00e1n had anything to do with the apostle. Traditionally used by fishermen as a source of drinking water. Reputed to have curative powers - most especially for ailments of the"], "https://research-squirrel-engineers.github.io/osm2lod/osmtag__historic": ["yes"], "https://research-squirrel-engineers.github.io/osm2lod/osmtag__name": ["Tobar P\u00e1rtal\u00e1in"], "https://research-squirrel-engineers.github.io/osm2lod/osmtag__natural": ["spring"], "https://research-squirrel-engineers.github.io/osm2lod/osmtag__place_of_worship": ["holy_well"], "https://research-squirrel-engineers.github.io/osm2lod/osmtag__religion": ["christian"], "https://research-squirrel-engineers.github.io/osm2lod/osmtag__tourism": ["attraction"]}, "geometry": {"type": "Point", "coordinates": [-9.2333785, 51.4898024], "crs": "4326"}, "crs": "EPSG:4326"}], "numberMatched": 1, "numberReturned": 1, "bbox": [-9.2333785, 51.4898024, -9.2333785, 51.4898024], "crs": "http://www.opengis.net/def/crs/EPSG/0/EPSG:4326"}