{"type": "FeatureCollection", "id": "https://research-squirrel-engineers.github.io/osm2lod/8663213269_geom", "name": "8663213269_geom", "features": [{"type": "Feature", "id": "http://openstreetmap.org/node/8663213269", "name": "", "dateprops": [], "properties": {"http://purl.org/dc/terms/created": ["2025-12-19T10:32:09.810385+00:00"], "http://purl.org/dc/terms/identifier": ["osm:node/8663213269"], "http://purl.org/dc/terms/isPartOf": ["https://research-squirrel-engineers.github.io/osm2lod/holywells__2025-12-19_103209Z"], "http://rdfs.org/ns/void#inDataset": ["http://openstreetmap.org/osm2rdf"], "http://www.opengis.net/ont/geosparql#hasGeometry": ["https://research-squirrel-engineers.github.io/osm2lod/8663213269_geom"], "http://www.w3.org/1999/02/22-rdf-syntax-ns#type": ["http://www.cidoc-crm.org/cidoc-crm/E26_Physical_Feature", "http://www.w3.org/ns/dcat#Dataset", "https://research-squirrel-engineers.github.io/osm2lod/OSMEntity"], "http://www.w3.org/2000/01/rdf-schema#label": ["Saint Anthony's Well"], "http://www.w3.org/2002/07/owl#sameAs": ["http://wikidata.org/entity/Q33097333"], "http://xmlns.com/foaf/0.1/primaryTopic": ["http://openstreetmap.org/node/8663213269"], "https://research-squirrel-engineers.github.io/osm2lod/exportType": ["holywells"], "https://research-squirrel-engineers.github.io/osm2lod/osmtag__denomination": ["roman_catholic"], "https://research-squirrel-engineers.github.io/osm2lod/osmtag__name": ["Saint Anthony's Well"], "https://research-squirrel-engineers.github.io/osm2lod/osmtag__natural": ["spring"], "https://research-squirrel-engineers.github.io/osm2lod/osmtag__place_of_worship": ["holy_well"], "https://research-squirrel-engineers.github.io/osm2lod/osmtag__religion": ["christian"], "https://research-squirrel-engineers.github.io/osm2lod/osmtag__wikidata": ["Q33097333"]}, "geometry": {"type": "Point", "coordinates": [-7.5924164, 53.2641605], "crs": "4326"}, "crs": "EPSG:4326"}], "numberMatched": 1, "numberReturned": 1, "bbox": [-7.5924164, 53.2641605, -7.5924164, 53.2641605], "crs": "http://www.opengis.net/def/crs/EPSG/0/EPSG:4326"}