{"type": "FeatureCollection", "id": "https://research-squirrel-engineers.github.io/osm2lod/12794210135_geom", "name": "12794210135_geom", "features": [{"type": "Feature", "id": "http://openstreetmap.org/node/12794210135", "name": "", "dateprops": [], "properties": {"http://purl.org/dc/terms/created": ["2025-12-19T10:32:09.810385+00:00"], "http://purl.org/dc/terms/identifier": ["osm:node/12794210135"], "http://purl.org/dc/terms/isPartOf": ["https://research-squirrel-engineers.github.io/osm2lod/holywells__2025-12-19_103209Z"], "http://rdfs.org/ns/void#inDataset": ["http://openstreetmap.org/osm2rdf"], "http://www.opengis.net/ont/geosparql#hasGeometry": ["https://research-squirrel-engineers.github.io/osm2lod/12794210135_geom"], "http://www.w3.org/1999/02/22-rdf-syntax-ns#type": ["http://www.cidoc-crm.org/cidoc-crm/E26_Physical_Feature", "http://www.w3.org/ns/dcat#Dataset", "https://research-squirrel-engineers.github.io/osm2lod/OSMEntity"], "http://www.w3.org/2000/01/rdf-schema#label": ["Tobernaveenoy"], "http://xmlns.com/foaf/0.1/primaryTopic": ["http://openstreetmap.org/node/12794210135"], "https://research-squirrel-engineers.github.io/osm2lod/exportType": ["holywells"], "https://research-squirrel-engineers.github.io/osm2lod/osmtag__name": ["Tobernaveenoy"], "https://research-squirrel-engineers.github.io/osm2lod/osmtag__natural": ["spring"], "https://research-squirrel-engineers.github.io/osm2lod/osmtag__place_of_worship": ["holy_well"]}, "geometry": {"type": "Point", "coordinates": [-6.7067585, 53.7899224], "crs": "4326"}, "crs": "EPSG:4326"}], "numberMatched": 1, "numberReturned": 1, "bbox": [-6.7067585, 53.7899224, -6.7067585, 53.7899224], "crs": "http://www.opengis.net/def/crs/EPSG/0/EPSG:4326"}