{"type": "FeatureCollection", "id": "https://research-squirrel-engineers.github.io/osm2lod/8814442373_geom", "name": "8814442373_geom", "features": [{"type": "Feature", "id": "http://openstreetmap.org/node/8814442373", "name": "", "dateprops": [], "properties": {"http://purl.org/dc/terms/created": ["2025-12-19T10:32:12.014823+00:00"], "http://purl.org/dc/terms/identifier": ["osm:node/8814442373"], "http://purl.org/dc/terms/isPartOf": ["https://research-squirrel-engineers.github.io/osm2lod/ci__2025-12-19_103212Z"], "http://rdfs.org/ns/void#inDataset": ["http://openstreetmap.org/osm2rdf"], "http://www.opengis.net/ont/geosparql#hasGeometry": ["https://research-squirrel-engineers.github.io/osm2lod/8814442373_geom"], "http://www.w3.org/1999/02/22-rdf-syntax-ns#type": ["http://www.cidoc-crm.org/cidoc-crm/E55_Place", "http://www.w3.org/ns/dcat#Dataset", "https://research-squirrel-engineers.github.io/osm2lod/OSMEntity"], "http://www.w3.org/2000/01/rdf-schema#label": ["\u041a\u043e\u0437\u0430\u0440\u043d\u0438\u043a\u0430"], "http://www.w3.org/2002/07/owl#sameAs": ["http://wikidata.org/entity/Q2037533"], "http://xmlns.com/foaf/0.1/primaryTopic": ["http://openstreetmap.org/node/8814442373"], "https://research-squirrel-engineers.github.io/osm2lod/exportType": ["ci"], "https://research-squirrel-engineers.github.io/osm2lod/osmtag__name": ["\u041a\u043e\u0437\u0430\u0440\u043d\u0438\u043a\u0430"], "https://research-squirrel-engineers.github.io/osm2lod/osmtag__natural": ["cave_entrance"], "https://research-squirrel-engineers.github.io/osm2lod/osmtag__wikidata": ["Q2037533"]}, "geometry": {"type": "Point", "coordinates": [22.7024397, 43.6518818], "crs": "4326"}, "crs": "EPSG:4326"}], "numberMatched": 1, "numberReturned": 1, "bbox": [22.7024397, 43.6518818, 22.7024397, 43.6518818], "crs": "http://www.opengis.net/def/crs/EPSG/0/EPSG:4326"}