{"type": "FeatureCollection", "id": "http://openstreetmap.org/E55_Place_collection", "name": "E55_Place Instances Collection", "features": [{"type": "Feature", "id": "http://openstreetmap.org/node/13200943487", "name": "Dehner Maar (13200943487)", "dateprops": [], "properties": {}, "geometry": {"type": "Point", "coordinates": [6.5064981, 50.2923379], "crs": "4326"}}, {"type": "Feature", "id": "http://openstreetmap.org/node/13386703821", "name": "AU3 (13386703821)", "dateprops": [], "properties": {}, "geometry": {"type": "Point", "coordinates": [6.5951003, 50.2824961], "crs": "4326"}}, {"type": "Feature", "id": "http://openstreetmap.org/node/13386786938", "name": "AU4 (13386786938)", "dateprops": [], "properties": {}, "geometry": {"type": "Point", "coordinates": [6.5949806, 50.2821054], "crs": "4326"}}, {"type": "Feature", "id": "http://openstreetmap.org/node/13200955773", "name": "Auel Maar (13200955773)", "dateprops": [], "properties": {}, "geometry": {"type": "Point", "coordinates": [6.5933215, 50.2775941], "crs": "4326"}}, {"type": "Feature", "id": "http://openstreetmap.org/node/13386723672", "name": "DE4 (13386723672)", "dateprops": [], "properties": {}, "geometry": {"type": "Point", "coordinates": [6.5065854, 50.2927959], "crs": "4326"}}], "numberMatched": 5, "numberReturned": 5, "bbox": [6.5064981, 50.2775941, 6.5951003, 50.2927959], "crs": "http://www.opengis.net/def/crs/EPSG/0/4326"}